<?xml version="1.0" encoding="UTF-8"?>
<objects serializationModel="Studio.02.02.00">
	<object class="AudioFile" id="{c339826c-42cf-4175-aa30-b8cd8aac8bbb}">
		<property name="assetPath">
			<value>Minecraft - Cave Sounds.mp3</value>
		</property>
		<property name="isStreaming">
			<value>true</value>
		</property>
		<property name="frequencyInKHz">
			<value>44.0999985</value>
		</property>
		<property name="channelCount">
			<value>2</value>
		</property>
		<property name="length">
			<value>143.9869387755102</value>
		</property>
		<relationship name="masterAssetFolder">
			<destination>{79530745-d8f0-4c51-bf33-b4fd37315e8c}</destination>
		</relationship>
	</object>
</objects>
